{
	"name": "ScheduleTrigger",
	"properties": {
		"annotations": [
			"ScheduleTrigger1st package"
		],
		"runtimeState": "Stopped",
		"pipelines": [
			{
				"pipelineReference": {
					"referenceName": "pipeline1",
					"type": "PipelineReference"
				}
			}
		],
		"type": "ScheduleTrigger",
		"typeProperties": {
			"recurrence": {
				"frequency": "Hour",
				"interval": 1,
				"startTime": "2025-05-23T07:10:00",
				"endTime": "2025-05-24T08:55:43",
				"timeZone": "India Standard Time"
			}
		}
	}
}